Metadata-Version: 2.1
Name: homebrewery-to-libris
Version: 1.1.0
Summary: Converter between homebrewery and libris markdown formats.
Home-page: https://github.com/lazy-scrivener-games/homebrewery-to-libris
Author: Chris Muller
Author-email: chris@lazyscrivenergames.com
License: MIT
Download-URL: https://github.com/lazy-scrivener-games/homebrewery-to-libris/archive/refs/tags/v1.1.tar.gz
Keywords: utility,pdf,html,markdown,conversion,book,roleplaying,game,homebrewery,libris
Platform: UNKNOWN
Classifier: Development Status :: 5 - Production/Stable
Classifier: Intended Audience :: End Users/Desktop
Classifier: Topic :: Text Processing :: Markup :: Markdown
Classifier: License :: OSI Approved :: MIT License
Classifier: Programming Language :: Python :: 3
Classifier: Programming Language :: Python :: 3.6
Classifier: Programming Language :: Python :: 3.7
Classifier: Programming Language :: Python :: 3.8
Classifier: Programming Language :: Python :: 3.9
License-File: LICENSE.txt
